datalake/__init__.py
datalake/datalake.py
datalake/api_objects/__init__.py
datalake/api_objects/bulk_search_task.py
datalake/common/__init__.py
datalake/common/atom.py
datalake/common/atom_type.py
datalake/common/config.py
datalake/common/logger.py
datalake/common/output.py
datalake/common/throttler.py
datalake/common/token_manager.py
datalake/common/utils.py
datalake/common/warn.py
datalake/config/endpoints.json
datalake/endpoints/__init__.py
datalake/endpoints/advanced_search.py
datalake/endpoints/bulk_search.py
datalake/endpoints/endpoint.py
datalake/endpoints/filtered_tag_subcategory.py
datalake/endpoints/sightings.py
datalake/endpoints/tags.py
datalake/endpoints/threats.py
datalake/miscellaneous/__init__.py
datalake/miscellaneous/search_watch.py
datalake_scripts/__init__.py
datalake_scripts/cli.py
datalake_scripts/common/__init__.py
datalake_scripts/common/base_engine.py
datalake_scripts/common/base_script.py
datalake_scripts/common/mixins.py
datalake_scripts/engines/__init__.py
datalake_scripts/engines/get_engine.py
datalake_scripts/engines/post_engine.py
datalake_scripts/helper_scripts/__init__.py
datalake_scripts/helper_scripts/output_builder.py
datalake_scripts/helper_scripts/utils.py
datalake_scripts/scripts/__init__.py
datalake_scripts/scripts/add_comments.py
datalake_scripts/scripts/add_tags.py
datalake_scripts/scripts/add_threats.py
datalake_scripts/scripts/advanced_search.py
datalake_scripts/scripts/bulk_lookup_threats.py
datalake_scripts/scripts/edit_score.py
datalake_scripts/scripts/get_atom_values.py
datalake_scripts/scripts/get_filtered_tag_subcategory.py
datalake_scripts/scripts/get_query_hash.py
datalake_scripts/scripts/get_threats_by_hashkey.py
datalake_scripts/scripts/get_threats_from_query_hash.py
datalake_scripts/scripts/lookup_threats.py
datalake_scripts/scripts/search_watch.py
tests/__init__.py
tests/conftest.py
tests/common/__init__.py
tests/common/fixture.py
tests/common/test_output.py
tests/common/test_utils.py
tests/lib/__init__.py
datalake_scripts-2.7.4.dist-info/METADATA
datalake_scripts-2.7.4.dist-info/WHEEL
datalake_scripts-2.7.4.dist-info/entry_points.txt
datalake_scripts-2.7.4.dist-info/top_level.txt
datalake_scripts-2.7.4.dist-info/RECORD
