Metadata-Version: 2.1
Name: datalake-scripts
Version: 2.7.4
Summary: A collection of scripts to easily use the API of OCD Datalake
Home-page: https://github.com/cert-orangecyberdefense/datalake/
Author: OCD
Author-email: cert-contact.ocd@orange.com
License: UNKNOWN
Platform: UNKNOWN
Classifier: Programming Language :: Python :: 3.7
Classifier: Programming Language :: Python :: 3.8
Classifier: Programming Language :: Python :: 3.9
Classifier: Programming Language :: Python :: 3.10
Classifier: Operating System :: POSIX :: Linux
Classifier: Environment :: Console
Classifier: Topic :: Security
Classifier: Natural Language :: English
Requires-Python: >=3.6
Requires-Dist: requests
Requires-Dist: halo
Requires-Dist: prettytable
